{"telemetry_id":"4svkvn08nyu6bolj","slug":"exercise-postcard","agent":"vscode","tutorial_started_at":1746535322446,"last_interaction_at":1746543360987,"steps":[{"slug":"00-welcome","position":0,"files":[{"path":".learn/exercises/00-welcome/README.es.md","name":"README.es.md","hidden":true},{"path":".learn/exercises/00-welcome/README.md","name":"README.md","hidden":true}],"ai_interactions":[],"compilations":[{"starting_at":1746535489358,"source_code":"","stdout":"U3VjY2Vzc2Z1bGx5IGJ1aWx0IHlvdXIgSFRNTA==","ended_at":"2025-05-06T12:44:49.359Z","exit_code":0}],"tests":[],"is_testeable":false,"quiz_submissions":[]},{"slug":"01-design","position":1,"files":[{"path":".learn/exercises/01-design/README.es.md","name":"README.es.md","hidden":true},{"path":".learn/exercises/01-design/README.md","name":"README.md","hidden":true}],"ai_interactions":[],"compilations":[],"tests":[],"is_testeable":false,"quiz_submissions":[],"opened_at":1746535501501,"completed_at":1746535503801},{"slug":"02-create-index","position":2,"files":[{"path":".learn/exercises/02-create-index/README.es.md","name":"README.es.md","hidden":true},{"path":".learn/exercises/02-create-index/README.md","name":"README.md","hidden":true},{"path":".learn/exercises/02-create-index/test.js","name":"test.js","hidden":true}],"ai_interactions":[],"compilations":[],"tests":[{"starting_at":1746535525089,"ended_at":1746535527486,"source_code":"","stdout":"G1szMm3inIUgQWxsIHRlc3RzIHBhc3NlZCBzdWNjZXNzZnVsbHkhG1szOW0=","stderr":"","exit_code":0}],"is_testeable":true,"quiz_submissions":[],"opened_at":1746535503801,"completed_at":1746535527487},{"slug":"03-add-first-html","position":3,"files":[{"path":".learn/exercises/03-add-first-html/README.es.md","name":"README.es.md","hidden":true},{"path":".learn/exercises/03-add-first-html/README.md","name":"README.md","hidden":true}],"ai_interactions":[],"compilations":[{"starting_at":1746535540275,"source_code":"","stdout":"U3VjY2Vzc2Z1bGx5IGJ1aWx0IHlvdXIgSFRNTA==","ended_at":"2025-05-06T12:45:40.275Z","exit_code":0},{"starting_at":1746535554482,"source_code":"","stdout":"U3VjY2Vzc2Z1bGx5IGJ1aWx0IHlvdXIgSFRNTA==","ended_at":"2025-05-06T12:45:54.482Z","exit_code":0}],"tests":[],"is_testeable":false,"quiz_submissions":[],"opened_at":1746535529182,"completed_at":1746535563971},{"slug":"04-build-the-website","position":4,"files":[{"path":".learn/exercises/04-build-the-website/README.es.md","name":"README.es.md","hidden":true},{"path":".learn/exercises/04-build-the-website/README.md","name":"README.md","hidden":true}],"ai_interactions":[],"compilations":[{"starting_at":1746535619141,"source_code":"","stdout":"U3VjY2Vzc2Z1bGx5IGJ1aWx0IHlvdXIgSFRNTA==","ended_at":"2025-05-06T12:46:59.141Z","exit_code":0}],"tests":[],"is_testeable":false,"quiz_submissions":[],"opened_at":1746535563971,"completed_at":1746535622624},{"slug":"05-how-to-start","position":5,"files":[{"path":".learn/exercises/05-how-to-start/README.es.md","name":"README.es.md","hidden":true},{"path":".learn/exercises/05-how-to-start/README.md","name":"README.md","hidden":true}],"ai_interactions":[],"compilations":[],"tests":[],"is_testeable":false,"quiz_submissions":[],"opened_at":1746535622624,"completed_at":1746535637543},{"slug":"06-lets-start-building","position":6,"files":[{"path":".learn/exercises/06-lets-start-building/README.es.md","name":"README.es.md","hidden":true},{"path":".learn/exercises/06-lets-start-building/README.md","name":"README.md","hidden":true},{"path":".learn/exercises/06-lets-start-building/test.js","name":"test.js","hidden":true}],"ai_interactions":[],"compilations":[],"tests":[{"starting_at":1746535676696,"ended_at":1746535678255,"source_code":"","stdout":"G1szMm3inIUgQWxsIHRlc3RzIHBhc3NlZCBzdWNjZXNzZnVsbHkhG1szOW0=","stderr":"","exit_code":0}],"is_testeable":true,"quiz_submissions":[],"opened_at":1746535637543,"completed_at":1746535678255},{"slug":"07-the-first-div","position":7,"files":[{"path":".learn/exercises/07-the-first-div/README.es.md","name":"README.es.md","hidden":true},{"path":".learn/exercises/07-the-first-div/README.md","name":"README.md","hidden":true},{"path":".learn/exercises/07-the-first-div/test.js","name":"test.js","hidden":true}],"ai_interactions":[],"compilations":[{"starting_at":1746535824793,"source_code":"","stdout":"U3VjY2Vzc2Z1bGx5IGJ1aWx0IHlvdXIgSFRNTA==","ended_at":"2025-05-06T12:50:24.793Z","exit_code":0}],"tests":[{"starting_at":1746535830163,"ended_at":1746535831801,"source_code":"","stdout":"G1szMm3inIUgQWxsIHRlc3RzIHBhc3NlZCBzdWNjZXNzZnVsbHkhG1szOW0=","stderr":"","exit_code":0}],"is_testeable":true,"quiz_submissions":[],"opened_at":1746535680607,"completed_at":1746535831801},{"slug":"08-adding-styles","position":8,"files":[{"path":".learn/exercises/08-adding-styles/README.es.md","name":"README.es.md","hidden":true},{"path":".learn/exercises/08-adding-styles/README.md","name":"README.md","hidden":true},{"path":".learn/exercises/08-adding-styles/test.js","name":"test.js","hidden":true}],"ai_interactions":[],"compilations":[{"starting_at":1746535932626,"source_code":"","stdout":"U3VjY2Vzc2Z1bGx5IGJ1aWx0IHlvdXIgSFRNTA==","ended_at":"2025-05-06T12:52:12.626Z","exit_code":0},{"starting_at":1746535990075,"source_code":"","stdout":"U3VjY2Vzc2Z1bGx5IGJ1aWx0IHlvdXIgSFRNTA==","ended_at":"2025-05-06T12:53:10.075Z","exit_code":0},{"starting_at":1746536023920,"source_code":"","stdout":"U3VjY2Vzc2Z1bGx5IGJ1aWx0IHlvdXIgSFRNTA==","ended_at":"2025-05-06T12:53:43.920Z","exit_code":0},{"starting_at":1746536095690,"source_code":"","stdout":"U3VjY2Vzc2Z1bGx5IGJ1aWx0IHlvdXIgSFRNTA==","ended_at":"2025-05-06T12:54:55.690Z","exit_code":0}],"tests":[{"starting_at":1746536000383,"ended_at":1746536001772,"source_code":"","stdout":"G1szMm3inIUgQWxsIHRlc3RzIHBhc3NlZCBzdWNjZXNzZnVsbHkhG1szOW0=","stderr":"","exit_code":0}],"is_testeable":true,"quiz_submissions":[],"opened_at":1746535833828,"completed_at":1746536001772},{"slug":"08.1-red-borders","position":9,"files":[{"path":".learn/exercises/08.1-red-borders/README.es.md","name":"README.es.md","hidden":true},{"path":".learn/exercises/08.1-red-borders/README.md","name":"README.md","hidden":true},{"path":".learn/exercises/08.1-red-borders/test.js","name":"test.js","hidden":true}],"ai_interactions":[],"compilations":[{"starting_at":1746536152239,"source_code":"","stdout":"U3VjY2Vzc2Z1bGx5IGJ1aWx0IHlvdXIgSFRNTA==","ended_at":"2025-05-06T12:55:52.239Z","exit_code":0},{"starting_at":1746541432776,"source_code":"","stdout":"U3VjY2Vzc2Z1bGx5IGJ1aWx0IHlvdXIgSFRNTA==","ended_at":"2025-05-06T14:23:52.776Z","exit_code":0},{"starting_at":1746541568386,"source_code":"","stdout":"U3VjY2Vzc2Z1bGx5IGJ1aWx0IHlvdXIgSFRNTA==","ended_at":"2025-05-06T14:26:08.386Z","exit_code":0}],"tests":[{"starting_at":1746536164829,"ended_at":1746536166220,"source_code":"","stdout":"G1szMm3inIUgQWxsIHRlc3RzIHBhc3NlZCBzdWNjZXNzZnVsbHkhG1szOW0=","stderr":"","exit_code":0}],"is_testeable":true,"quiz_submissions":[],"opened_at":1746536003356,"completed_at":1746536166220},{"slug":"09-connecting-stylesheet","position":10,"files":[{"path":".learn/exercises/09-connecting-stylesheet/README.es.md","name":"README.es.md","hidden":true},{"path":".learn/exercises/09-connecting-stylesheet/README.md","name":"README.md","hidden":true},{"path":".learn/exercises/09-connecting-stylesheet/test.js","name":"test.js","hidden":true}],"ai_interactions":[],"compilations":[{"starting_at":1746541536569,"source_code":"","stdout":"U3VjY2Vzc2Z1bGx5IGJ1aWx0IHlvdXIgSFRNTA==","ended_at":"2025-05-06T14:25:36.569Z","exit_code":0}],"tests":[{"starting_at":1746536190144,"ended_at":1746536191702,"source_code":"","stdout":"G1szMm3inIUgQWxsIHRlc3RzIHBhc3NlZCBzdWNjZXNzZnVsbHkhG1szOW0=","stderr":"","exit_code":0}],"is_testeable":true,"quiz_submissions":[],"opened_at":1746536167811,"completed_at":1746536191703},{"slug":"10-center-postcard","position":11,"files":[{"path":".learn/exercises/10-center-postcard/README.es.md","name":"README.es.md","hidden":true},{"path":".learn/exercises/10-center-postcard/README.md","name":"README.md","hidden":true},{"path":".learn/exercises/10-center-postcard/test.js","name":"test.js","hidden":true}],"ai_interactions":[],"compilations":[{"starting_at":1746536237126,"source_code":"","stdout":"U3VjY2Vzc2Z1bGx5IGJ1aWx0IHlvdXIgSFRNTA==","ended_at":"2025-05-06T12:57:17.126Z","exit_code":0},{"starting_at":1746536310585,"source_code":"","stdout":"U3VjY2Vzc2Z1bGx5IGJ1aWx0IHlvdXIgSFRNTA==","ended_at":"2025-05-06T12:58:30.585Z","exit_code":0}],"tests":[{"starting_at":1746536314458,"ended_at":1746536316048,"source_code":"","stdout":"G1szMm3inIUgQWxsIHRlc3RzIHBhc3NlZCBzdWNjZXNzZnVsbHkhG1szOW0=","stderr":"","exit_code":0}],"is_testeable":true,"quiz_submissions":[],"opened_at":1746536193347,"completed_at":1746536316048},{"slug":"11-postcard-divisions","position":12,"files":[{"path":".learn/exercises/11-postcard-divisions/README.es.md","name":"README.es.md","hidden":true},{"path":".learn/exercises/11-postcard-divisions/README.md","name":"README.md","hidden":true},{"path":".learn/exercises/11-postcard-divisions/test.js","name":"test.js","hidden":true}],"ai_interactions":[],"compilations":[{"starting_at":1746536414697,"source_code":"","stdout":"U3VjY2Vzc2Z1bGx5IGJ1aWx0IHlvdXIgSFRNTA==","ended_at":"2025-05-06T13:00:14.698Z","exit_code":0}],"tests":[{"starting_at":1746536420406,"ended_at":1746536421963,"source_code":"","stdout":"G1szMm3inIUgQWxsIHRlc3RzIHBhc3NlZCBzdWNjZXNzZnVsbHkhG1szOW0=","stderr":"","exit_code":0}],"is_testeable":true,"quiz_submissions":[],"opened_at":1746536319079,"completed_at":1746536421963},{"slug":"11.1-header-content","position":13,"files":[{"path":".learn/exercises/11.1-header-content/README.es.md","name":"README.es.md","hidden":true},{"path":".learn/exercises/11.1-header-content/README.md","name":"README.md","hidden":true},{"path":".learn/exercises/11.1-header-content/solution.hide.css","name":"solution.hide.css","hidden":true},{"path":".learn/exercises/11.1-header-content/solution.hide.html","name":"solution.hide.html","hidden":true},{"path":".learn/exercises/11.1-header-content/test.js","name":"test.js","hidden":true}],"ai_interactions":[],"compilations":[{"starting_at":1746536507381,"source_code":"","stdout":"U3VjY2Vzc2Z1bGx5IGJ1aWx0IHlvdXIgSFRNTA==","ended_at":"2025-05-06T13:01:47.381Z","exit_code":0},{"starting_at":1746542018827,"source_code":"","stdout":"U3VjY2Vzc2Z1bGx5IGJ1aWx0IHlvdXIgSFRNTA==","ended_at":"2025-05-06T14:33:38.827Z","exit_code":0}],"tests":[{"starting_at":1746536519850,"ended_at":1746536521487,"source_code":"","stdout":"G1szMm3inIUgQWxsIHRlc3RzIHBhc3NlZCBzdWNjZXNzZnVsbHkhG1szOW0=","stderr":"","exit_code":0}],"is_testeable":true,"quiz_submissions":[],"opened_at":1746536423604,"completed_at":1746536521487},{"slug":"11.2-header-styles","position":14,"files":[{"path":".learn/exercises/11.2-header-styles/README.es.md","name":"README.es.md","hidden":true},{"path":".learn/exercises/11.2-header-styles/README.md","name":"README.md","hidden":true},{"path":".learn/exercises/11.2-header-styles/test.js","name":"test.js","hidden":true}],"ai_interactions":[],"compilations":[{"starting_at":1746536692525,"source_code":"","stdout":"U3VjY2Vzc2Z1bGx5IGJ1aWx0IHlvdXIgSFRNTA==","ended_at":"2025-05-06T13:04:52.525Z","exit_code":0},{"starting_at":1746541984236,"source_code":"","stdout":"U3VjY2Vzc2Z1bGx5IGJ1aWx0IHlvdXIgSFRNTA==","ended_at":"2025-05-06T14:33:04.236Z","exit_code":0},{"starting_at":1746542035494,"source_code":"","stdout":"U3VjY2Vzc2Z1bGx5IGJ1aWx0IHlvdXIgSFRNTA==","ended_at":"2025-05-06T14:33:55.494Z","exit_code":0},{"starting_at":1746542155833,"source_code":"","stdout":"U3VjY2Vzc2Z1bGx5IGJ1aWx0IHlvdXIgSFRNTA==","ended_at":"2025-05-06T14:35:55.833Z","exit_code":0},{"starting_at":1746542222450,"source_code":"","stdout":"U3VjY2Vzc2Z1bGx5IGJ1aWx0IHlvdXIgSFRNTA==","ended_at":"2025-05-06T14:37:02.450Z","exit_code":0},{"starting_at":1746542459954,"source_code":"","stdout":"U3VjY2Vzc2Z1bGx5IGJ1aWx0IHlvdXIgSFRNTA==","ended_at":"2025-05-06T14:40:59.954Z","exit_code":0}],"tests":[{"starting_at":1746536820441,"ended_at":1746536821959,"source_code":"","stdout":"G1szMm3inIUgQWxsIHRlc3RzIHBhc3NlZCBzdWNjZXNzZnVsbHkhG1szOW0=","stderr":"","exit_code":0}],"is_testeable":true,"quiz_submissions":[],"opened_at":1746536528276,"completed_at":1746536821959},{"slug":"12-split-postcard-body","position":15,"files":[{"path":".learn/exercises/12-split-postcard-body/README.es.md","name":"README.es.md","hidden":true},{"path":".learn/exercises/12-split-postcard-body/README.md","name":"README.md","hidden":true},{"path":".learn/exercises/12-split-postcard-body/test.js","name":"test.js","hidden":true}],"ai_interactions":[],"compilations":[{"starting_at":1746536912715,"source_code":"","stdout":"U3VjY2Vzc2Z1bGx5IGJ1aWx0IHlvdXIgSFRNTA==","ended_at":"2025-05-06T13:08:32.715Z","exit_code":0},{"starting_at":1746536943214,"source_code":"","stdout":"U3VjY2Vzc2Z1bGx5IGJ1aWx0IHlvdXIgSFRNTA==","ended_at":"2025-05-06T13:09:03.214Z","exit_code":0},{"starting_at":1746541767071,"source_code":"","stdout":"U3VjY2Vzc2Z1bGx5IGJ1aWx0IHlvdXIgSFRNTA==","ended_at":"2025-05-06T14:29:27.071Z","exit_code":0},{"starting_at":1746542097201,"source_code":"","stdout":"U3VjY2Vzc2Z1bGx5IGJ1aWx0IHlvdXIgSFRNTA==","ended_at":"2025-05-06T14:34:57.201Z","exit_code":0},{"starting_at":1746542168302,"source_code":"","stdout":"U3VjY2Vzc2Z1bGx5IGJ1aWx0IHlvdXIgSFRNTA==","ended_at":"2025-05-06T14:36:08.302Z","exit_code":0},{"starting_at":1746542200061,"source_code":"","stdout":"U3VjY2Vzc2Z1bGx5IGJ1aWx0IHlvdXIgSFRNTA==","ended_at":"2025-05-06T14:36:40.061Z","exit_code":0},{"starting_at":1746542340878,"source_code":"","stdout":"U3VjY2Vzc2Z1bGx5IGJ1aWx0IHlvdXIgSFRNTA==","ended_at":"2025-05-06T14:39:00.878Z","exit_code":0},{"starting_at":1746542433636,"source_code":"","stdout":"U3VjY2Vzc2Z1bGx5IGJ1aWx0IHlvdXIgSFRNTA==","ended_at":"2025-05-06T14:40:33.636Z","exit_code":0}],"tests":[{"starting_at":1746536970369,"ended_at":1746536971949,"source_code":"","stdout":"G1szMm3inIUgQWxsIHRlc3RzIHBhc3NlZCBzdWNjZXNzZnVsbHkhG1szOW0=","stderr":"","exit_code":0}],"is_testeable":true,"quiz_submissions":[],"opened_at":1746536824059,"completed_at":1746536971949},{"slug":"12.1-body-content","position":16,"files":[{"path":".learn/exercises/12.1-body-content/README.es.md","name":"README.es.md","hidden":true},{"path":".learn/exercises/12.1-body-content/README.md","name":"README.md","hidden":true},{"path":".learn/exercises/12.1-body-content/test.js","name":"test.js","hidden":true}],"ai_interactions":[],"compilations":[{"starting_at":1746537181157,"source_code":"","stdout":"U3VjY2Vzc2Z1bGx5IGJ1aWx0IHlvdXIgSFRNTA==","ended_at":"2025-05-06T13:13:01.157Z","exit_code":0},{"starting_at":1746538849989,"source_code":"","stdout":"U3VjY2Vzc2Z1bGx5IGJ1aWx0IHlvdXIgSFRNTA==","ended_at":"2025-05-06T13:40:49.989Z","exit_code":0},{"starting_at":1746539011729,"source_code":"","stdout":"U3VjY2Vzc2Z1bGx5IGJ1aWx0IHlvdXIgSFRNTA==","ended_at":"2025-05-06T13:43:31.729Z","exit_code":0},{"starting_at":1746539645376,"source_code":"","stdout":"U3VjY2Vzc2Z1bGx5IGJ1aWx0IHlvdXIgSFRNTA==","ended_at":"2025-05-06T13:54:05.376Z","exit_code":0},{"starting_at":1746539816900,"source_code":"","stdout":"U3VjY2Vzc2Z1bGx5IGJ1aWx0IHlvdXIgSFRNTA==","ended_at":"2025-05-06T13:56:56.900Z","exit_code":0},{"starting_at":1746539844143,"source_code":"","stdout":"U3VjY2Vzc2Z1bGx5IGJ1aWx0IHlvdXIgSFRNTA==","ended_at":"2025-05-06T13:57:24.143Z","exit_code":0},{"starting_at":1746539873296,"source_code":"","stdout":"U3VjY2Vzc2Z1bGx5IGJ1aWx0IHlvdXIgSFRNTA==","ended_at":"2025-05-06T13:57:53.296Z","exit_code":0},{"starting_at":1746539882992,"source_code":"","stdout":"U3VjY2Vzc2Z1bGx5IGJ1aWx0IHlvdXIgSFRNTA==","ended_at":"2025-05-06T13:58:02.992Z","exit_code":0},{"starting_at":1746539908204,"source_code":"","stdout":"U3VjY2Vzc2Z1bGx5IGJ1aWx0IHlvdXIgSFRNTA==","ended_at":"2025-05-06T13:58:28.204Z","exit_code":0},{"starting_at":1746541670061,"source_code":"","stdout":"U3VjY2Vzc2Z1bGx5IGJ1aWx0IHlvdXIgSFRNTA==","ended_at":"2025-05-06T14:27:50.061Z","exit_code":0},{"starting_at":1746542182050,"source_code":"","stdout":"U3VjY2Vzc2Z1bGx5IGJ1aWx0IHlvdXIgSFRNTA==","ended_at":"2025-05-06T14:36:22.050Z","exit_code":0},{"starting_at":1746542417206,"source_code":"","stdout":"U3VjY2Vzc2Z1bGx5IGJ1aWx0IHlvdXIgSFRNTA==","ended_at":"2025-05-06T14:40:17.206Z","exit_code":0},{"starting_at":1746543360987,"source_code":"","stdout":"U3VjY2Vzc2Z1bGx5IGJ1aWx0IHlvdXIgSFRNTA==","ended_at":"2025-05-06T14:56:00.987Z","exit_code":0}],"tests":[{"starting_at":1746540024196,"ended_at":1746540025789,"source_code":"","stdout":"G1szMm3inIUgQWxsIHRlc3RzIHBhc3NlZCBzdWNjZXNzZnVsbHkhG1szOW0=","stderr":"","exit_code":0}],"is_testeable":true,"quiz_submissions":[],"opened_at":1746536974118,"completed_at":1746540025789},{"slug":"13-check-your-code","position":17,"files":[{"path":".learn/exercises/13-check-your-code/README.es.md","name":"README.es.md","hidden":true},{"path":".learn/exercises/13-check-your-code/README.md","name":"README.md","hidden":true}],"ai_interactions":[],"compilations":[{"starting_at":1746540067476,"source_code":"","stdout":"U3VjY2Vzc2Z1bGx5IGJ1aWx0IHlvdXIgSFRNTA==","ended_at":"2025-05-06T14:01:07.476Z","exit_code":0},{"starting_at":1746540151263,"source_code":"","stdout":"U3VjY2Vzc2Z1bGx5IGJ1aWx0IHlvdXIgSFRNTA==","ended_at":"2025-05-06T14:02:31.263Z","exit_code":0},{"starting_at":1746540159017,"source_code":"","stdout":"U3VjY2Vzc2Z1bGx5IGJ1aWx0IHlvdXIgSFRNTA==","ended_at":"2025-05-06T14:02:39.017Z","exit_code":0},{"starting_at":1746540224914,"source_code":"","stdout":"U3VjY2Vzc2Z1bGx5IGJ1aWx0IHlvdXIgSFRNTA==","ended_at":"2025-05-06T14:03:44.914Z","exit_code":0},{"starting_at":1746540239928,"source_code":"","stdout":"U3VjY2Vzc2Z1bGx5IGJ1aWx0IHlvdXIgSFRNTA==","ended_at":"2025-05-06T14:03:59.928Z","exit_code":0},{"starting_at":1746540278340,"source_code":"","stdout":"U3VjY2Vzc2Z1bGx5IGJ1aWx0IHlvdXIgSFRNTA==","ended_at":"2025-05-06T14:04:38.340Z","exit_code":0},{"starting_at":1746540294178,"source_code":"","stdout":"U3VjY2Vzc2Z1bGx5IGJ1aWx0IHlvdXIgSFRNTA==","ended_at":"2025-05-06T14:04:54.178Z","exit_code":0},{"starting_at":1746540342328,"source_code":"","stdout":"U3VjY2Vzc2Z1bGx5IGJ1aWx0IHlvdXIgSFRNTA==","ended_at":"2025-05-06T14:05:42.328Z","exit_code":0},{"starting_at":1746540394093,"source_code":"","stdout":"U3VjY2Vzc2Z1bGx5IGJ1aWx0IHlvdXIgSFRNTA==","ended_at":"2025-05-06T14:06:34.093Z","exit_code":0},{"starting_at":1746540411877,"source_code":"","stdout":"U3VjY2Vzc2Z1bGx5IGJ1aWx0IHlvdXIgSFRNTA==","ended_at":"2025-05-06T14:06:51.877Z","exit_code":0},{"starting_at":1746540428698,"source_code":"","stdout":"U3VjY2Vzc2Z1bGx5IGJ1aWx0IHlvdXIgSFRNTA==","ended_at":"2025-05-06T14:07:08.698Z","exit_code":0},{"starting_at":1746540464828,"source_code":"","stdout":"U3VjY2Vzc2Z1bGx5IGJ1aWx0IHlvdXIgSFRNTA==","ended_at":"2025-05-06T14:07:44.828Z","exit_code":0},{"starting_at":1746540502094,"source_code":"","stdout":"U3VjY2Vzc2Z1bGx5IGJ1aWx0IHlvdXIgSFRNTA==","ended_at":"2025-05-06T14:08:22.094Z","exit_code":0},{"starting_at":1746540592714,"source_code":"","stdout":"U3VjY2Vzc2Z1bGx5IGJ1aWx0IHlvdXIgSFRNTA==","ended_at":"2025-05-06T14:09:52.714Z","exit_code":0},{"starting_at":1746540621676,"source_code":"","stdout":"U3VjY2Vzc2Z1bGx5IGJ1aWx0IHlvdXIgSFRNTA==","ended_at":"2025-05-06T14:10:21.676Z","exit_code":0},{"starting_at":1746540721374,"source_code":"","stdout":"U3VjY2Vzc2Z1bGx5IGJ1aWx0IHlvdXIgSFRNTA==","ended_at":"2025-05-06T14:12:01.374Z","exit_code":0},{"starting_at":1746540748818,"source_code":"","stdout":"U3VjY2Vzc2Z1bGx5IGJ1aWx0IHlvdXIgSFRNTA==","ended_at":"2025-05-06T14:12:28.818Z","exit_code":0},{"starting_at":1746540766716,"source_code":"","stdout":"U3VjY2Vzc2Z1bGx5IGJ1aWx0IHlvdXIgSFRNTA==","ended_at":"2025-05-06T14:12:46.716Z","exit_code":0},{"starting_at":1746540802081,"source_code":"","stdout":"U3VjY2Vzc2Z1bGx5IGJ1aWx0IHlvdXIgSFRNTA==","ended_at":"2025-05-06T14:13:22.081Z","exit_code":0},{"starting_at":1746540842014,"source_code":"","stdout":"U3VjY2Vzc2Z1bGx5IGJ1aWx0IHlvdXIgSFRNTA==","ended_at":"2025-05-06T14:14:02.014Z","exit_code":0},{"starting_at":1746540902137,"source_code":"","stdout":"U3VjY2Vzc2Z1bGx5IGJ1aWx0IHlvdXIgSFRNTA==","ended_at":"2025-05-06T14:15:02.137Z","exit_code":0},{"starting_at":1746540913814,"source_code":"","stdout":"U3VjY2Vzc2Z1bGx5IGJ1aWx0IHlvdXIgSFRNTA==","ended_at":"2025-05-06T14:15:13.814Z","exit_code":0},{"starting_at":1746540950324,"source_code":"","stdout":"U3VjY2Vzc2Z1bGx5IGJ1aWx0IHlvdXIgSFRNTA==","ended_at":"2025-05-06T14:15:50.324Z","exit_code":0},{"starting_at":1746540971334,"source_code":"","stdout":"U3VjY2Vzc2Z1bGx5IGJ1aWx0IHlvdXIgSFRNTA==","ended_at":"2025-05-06T14:16:11.334Z","exit_code":0},{"starting_at":1746541044859,"source_code":"","stdout":"U3VjY2Vzc2Z1bGx5IGJ1aWx0IHlvdXIgSFRNTA==","ended_at":"2025-05-06T14:17:24.859Z","exit_code":0},{"starting_at":1746541123793,"source_code":"","stdout":"U3VjY2Vzc2Z1bGx5IGJ1aWx0IHlvdXIgSFRNTA==","ended_at":"2025-05-06T14:18:43.793Z","exit_code":0},{"starting_at":1746541297250,"source_code":"","stdout":"U3VjY2Vzc2Z1bGx5IGJ1aWx0IHlvdXIgSFRNTA==","ended_at":"2025-05-06T14:21:37.250Z","exit_code":0},{"starting_at":1746541316059,"source_code":"","stdout":"U3VjY2Vzc2Z1bGx5IGJ1aWx0IHlvdXIgSFRNTA==","ended_at":"2025-05-06T14:21:56.059Z","exit_code":0},{"starting_at":1746541358542,"source_code":"","stdout":"U3VjY2Vzc2Z1bGx5IGJ1aWx0IHlvdXIgSFRNTA==","ended_at":"2025-05-06T14:22:38.542Z","exit_code":0},{"starting_at":1746541366163,"source_code":"","stdout":"U3VjY2Vzc2Z1bGx5IGJ1aWx0IHlvdXIgSFRNTA==","ended_at":"2025-05-06T14:22:46.163Z","exit_code":0},{"starting_at":1746541377288,"source_code":"","stdout":"U3VjY2Vzc2Z1bGx5IGJ1aWx0IHlvdXIgSFRNTA==","ended_at":"2025-05-06T14:22:57.288Z","exit_code":0}],"tests":[],"is_testeable":false,"quiz_submissions":[],"opened_at":1746535415137,"completed_at":1746535501501},{"slug":"14-goodbye","position":18,"files":[{"path":".learn/exercises/14-goodbye/README.es.md","name":"README.es.md","hidden":true},{"path":".learn/exercises/14-goodbye/README.md","name":"README.md","hidden":true}],"ai_interactions":[],"compilations":[],"tests":[],"is_testeable":false,"quiz_submissions":[],"opened_at":1746540165196,"completed_at":1746540188677}],"workout_session":[{"started_at":1746535322446,"ended_at":1746543120509},{"started_at":1746543302390}]}